auto_serialize/__init__.py
auto_serialize/_auto_serialize.py
auto_serialize/interfaces.py
auto_serialize-1.0.0.dist-info/LICENSE.txt
auto_serialize-1.0.0.dist-info/METADATA
auto_serialize-1.0.0.dist-info/WHEEL
auto_serialize-1.0.0.dist-info/top_level.txt
auto_serialize-1.0.0.dist-info/RECORD
