Metadata-Version: 2.1
Name: auto_serialize
Version: 1.0.0
Summary: A simple serialization library for Python.
Author-email: Dr Richard Brearton <richardbrearton@gmail.com>
License: MIT License
Project-URL: Homepage, https://github.com/RBrearton/auto_serialize
Project-URL: Bug Reports, https://github.com/RBrearton/auto_serialize/issues
Project-URL: Source, https://github.com/RBrearton/auto_serialize
Classifier: Development Status :: 4 - Beta
Classifier: Intended Audience :: Developers
Classifier: Programming Language :: Python :: 3.11
Classifier: Programming Language :: Python :: 3.12
Classifier: Programming Language :: Python :: 3 :: Only
Requires-Python: >=3.11
License-File: LICENSE.txt
Requires-Dist: orjson
Requires-Dist: pyyaml
Requires-Dist: numpy
